list_all_data/__init__.py
list_all_data/cli_script.py
list_all_data/libary.py
lad_cli-1.0.2.dist-info/LICENSE
lad_cli-1.0.2.dist-info/METADATA
lad_cli-1.0.2.dist-info/WHEEL
lad_cli-1.0.2.dist-info/entry_points.txt
lad_cli-1.0.2.dist-info/top_level.txt
lad_cli-1.0.2.dist-info/RECORD
