Metadata-Version: 2.1
Name: lad-cli
Version: 1.0.2
Summary: A cli script to detect and list files including Alternate Data Streams under linux using the getfattr command.
Home-page: https://github.com/wahlflo/lad
Author: Florian Wahl
Author-email: florian.wahl.developer@gmail.com
License: UNKNOWN
Platform: UNKNOWN
Classifier: Programming Language :: Python :: 3
Classifier: License :: OSI Approved :: MIT License
Classifier: Operating System :: Unix
Requires-Dist: cli-formatter (>=1.0.0)
Requires-Dist: python-dateutil (>=2.8.1)
Requires-Dist: psutil (>=5.7.0)
